dabeplech/__init__.py
dabeplech/base.py
dabeplech/doi.py
dabeplech/hal.py
dabeplech/kegg.py
dabeplech/metagenedb.py
dabeplech/models/__init__.py
dabeplech/models/kegg.py
dabeplech/models/ncbi_taxonomy.py
dabeplech/ols.py
dabeplech/parsers/__init__.py
dabeplech/parsers/base.py
dabeplech/parsers/kegg/__init__.py
dabeplech/parsers/kegg/base.py
dabeplech/parsers/kegg/link.py
dabeplech/parsers/kegg/list.py
dabeplech/parsers/kegg/module.py
dabeplech/parsers/kegg/orthology.py
dabeplech/parsers/kegg/pathway.py
dabeplech/parsers/kegg/reference.py
dabeplech/pdbe.py
dabeplech/togows.py
dabeplech/version.py
dabeplech-0.6.0.dist-info/LICENSE
dabeplech-0.6.0.dist-info/WHEEL
dabeplech-0.6.0.dist-info/METADATA
dabeplech-0.6.0.dist-info/RECORD
